vmlab_mask-0.1.5.dist-info/METADATA
vmlab_mask-0.1.5.dist-info/WHEEL
vmlab_mask/__init__.py
vmlab_mask/vmlab_mask.cp312-win_amd64.pyd
vmlab_mask-0.1.5.dist-info/RECORD
